toolscore/__init__.py
toolscore/baseline.py
toolscore/capture.py
toolscore/cli.py
toolscore/comparison.py
toolscore/core.py
toolscore/debug.py
toolscore/explainer.py
toolscore/pytest_plugin.py
toolscore/adapters/__init__.py
toolscore/adapters/anthropic.py
toolscore/adapters/base.py
toolscore/adapters/custom.py
toolscore/adapters/gemini.py
toolscore/adapters/langchain.py
toolscore/adapters/mcp.py
toolscore/adapters/openai.py
toolscore/generators/__init__.py
toolscore/generators/synthetic.py
toolscore/metrics/__init__.py
toolscore/metrics/accuracy.py
toolscore/metrics/arguments.py
toolscore/metrics/cost.py
toolscore/metrics/cost_estimator.py
toolscore/metrics/efficiency.py
toolscore/metrics/llm_judge.py
toolscore/metrics/sequence.py
toolscore/metrics/side_effects.py
toolscore/metrics/tool_correctness.py
toolscore/metrics/trajectory.py
toolscore/reports/__init__.py
toolscore/reports/console_report.py
toolscore/reports/csv_report.py
toolscore/reports/html_report.py
toolscore/reports/json_report.py
toolscore/reports/markdown_report.py
toolscore/validators/__init__.py
toolscore/validators/database.py
toolscore/validators/filesystem.py
toolscore/validators/http.py
toolscore/validators/schema.py
tool_scorer-1.4.2.dist-info/METADATA
tool_scorer-1.4.2.dist-info/WHEEL
tool_scorer-1.4.2.dist-info/entry_points.txt
tool_scorer-1.4.2.dist-info/licenses/LICENSE
tool_scorer-1.4.2.dist-info/RECORD
