Metadata-Version: 2.4
Name: tool-scorer
Version: 1.4.2
Summary: Pytest for LLM agents. Self-explaining metrics show exactly WHY your agent failed. Regression testing catches degradation before deployment. GitHub Action for one-click CI/CD. Supports OpenAI, Anthropic, Gemini.
Project-URL: Homepage, https://github.com/yotambraun/toolscore
Project-URL: Documentation, https://github.com/yotambraun/toolscore#readme
Project-URL: Repository, https://github.com/yotambraun/toolscore
Project-URL: Issues, https://github.com/yotambraun/toolscore/issues
Project-URL: Changelog, https://github.com/yotambraun/toolscore/blob/main/CHANGELOG.md
Project-URL: Bug Tracker, https://github.com/yotambraun/toolscore/issues
Project-URL: Source Code, https://github.com/yotambraun/toolscore
Project-URL: PyPI, https://pypi.org/project/tool-scorer/
Author-email: Yotam Barun <yotambarun93@gmail.com>
License: Apache-2.0
License-File: LICENSE
Keywords: accuracy,agent-evaluation,agent-qa,agent-testing,ai-agents,ai-testing,anthropic,baseline-comparison,benchmarking,ci-cd,claude,claude-tools,evaluation,function-calling,function-calling-test,gemini,gemini-tools,github-action,gpt,langchain,langsmith-alternative,llm,llm-benchmark,llm-evaluation,llm-testing,mcp,metrics,model-comparison,model-context-protocol,openai,openai-functions,prompt-engineering,pytest,quality-assurance,quality-gates,regression-testing,self-explaining-metrics,test-auto
Classifier: Development Status :: 4 - Beta
Classifier: Framework :: Pytest
Classifier: Intended Audience :: Developers
Classifier: Intended Audience :: Science/Research
Classifier: License :: OSI Approved :: Apache Software License
Classifier: Operating System :: OS Independent
Classifier: Programming Language :: Python :: 3
Classifier: Programming Language :: Python :: 3.10
Classifier: Programming Language :: Python :: 3.11
Classifier: Programming Language :: Python :: 3.12
Classifier: Programming Language :: Python :: 3.13
Classifier: Topic :: Scientific/Engineering :: Artificial Intelligence
Classifier: Topic :: Software Development :: Libraries :: Python Modules
Classifier: Topic :: Software Development :: Quality Assurance
Classifier: Topic :: Software Development :: Testing
Classifier: Topic :: Software Development :: Testing :: Unit
Classifier: Typing :: Typed
Requires-Python: >=3.10
Requires-Dist: click>=8.1.0
Requires-Dist: jinja2>=3.1.0
Requires-Dist: python-levenshtein>=0.25.0
Requires-Dist: rich>=13.0.0
Provides-Extra: all
Requires-Dist: httpx>=0.27.0; extra == 'all'
Requires-Dist: langchain>=0.1.0; extra == 'all'
Requires-Dist: openai>=1.0.0; extra == 'all'
Provides-Extra: dev
Requires-Dist: mypy>=1.8.0; extra == 'dev'
Requires-Dist: pytest-cov>=5.0.0; extra == 'dev'
Requires-Dist: pytest>=8.0.0; extra == 'dev'
Requires-Dist: python-semantic-release>=9.0.0; extra == 'dev'
Requires-Dist: ruff>=0.6.0; extra == 'dev'
Requires-Dist: types-click; extra == 'dev'
Provides-Extra: docs
Requires-Dist: myst-parser>=2.0.0; extra == 'docs'
Requires-Dist: sphinx-autodoc-typehints>=2.0.0; extra == 'docs'
Requires-Dist: sphinx-rtd-theme>=2.0.0; extra == 'docs'
Requires-Dist: sphinx>=7.0.0; extra == 'docs'
Provides-Extra: http
Requires-Dist: httpx>=0.27.0; extra == 'http'
Provides-Extra: langchain
Requires-Dist: langchain>=0.1.0; extra == 'langchain'
Provides-Extra: llm
Requires-Dist: openai>=1.0.0; extra == 'llm'
